[
  {
    "date": "2025-11-08T00:00:00.000Z",
    "excerpt": "<p>A young man returns to the family sheep farm to find his older brother’s genetic experiments have turned the flock into bloodthirsty monsters.</p>",
    "genres": [
      "Comedy",
      "Horror",
      "Sci-Fi"
    ],
    "image": "/_astro/black-sheep-2006.DeoMVv_i_2tG6BN.png",
    "slug": "black-sheep-2006",
    "stars": 2.5,
    "title": "Black Sheep",
    "year": "2006"
  },
  {
    "date": "2025-11-08T00:00:00.000Z",
    "excerpt": "<p>A group of parapsychologists out to cleanse a haunted house fall prey to a murderous warlock’s spirit.</p>",
    "genres": [
      "Action",
      "Horror",
      "Thriller"
    ],
    "image": "/_astro/witchtrap-1989.yOBJ5olZ_ZlAx4o.png",
    "slug": "witchtrap-1989",
    "stars": 3.5,
    "title": "Witchtrap",
    "year": "1989"
  },
  {
    "date": "2025-11-06T00:00:00.000Z",
    "excerpt": "<p>Bond trader Tom Hanks and mistress Melanie Griffith take a wrong turn into the South Bronx, hit a local kid, and flee—sparking a media circus fanned by alcoholic journalist Bruce Willis.</p>",
    "genres": [
      "Comedy",
      "Drama",
      "Romance"
    ],
    "image": "/_astro/the-bonfire-of-the-vanities-1990.CnEgjcoj_2kDzzl.png",
    "slug": "the-bonfire-of-the-vanities-1990",
    "stars": 2,
    "title": "The Bonfire of the Vanities",
    "year": "1990"
  },
  {
    "date": "2025-11-05T00:00:00.000Z",
    "excerpt": "<p>Society gentleman Errol Flynn leads a double-life as a mystery writer and gets caught up in a real murder case.</p>",
    "genres": [
      "Comedy",
      "Crime",
      "Mystery"
    ],
    "image": "/_astro/footsteps-in-the-dark-1941.zHUnVzmV_1FNSPC.png",
    "slug": "footsteps-in-the-dark-1941",
    "stars": 1,
    "title": "Footsteps in the Dark",
    "year": "1941"
  },
  {
    "date": "2025-11-03T00:00:00.000Z",
    "excerpt": "<p>A moonlighting private eye falls for the fashion designer he’s surveilling after discovering her secret life as a prostitute—but a deranged street preacher is watching too.</p>",
    "genres": [
      "Drama",
      "Romance",
      "Thriller"
    ],
    "image": "/_astro/crimes-of-passion-1984.B-PIgxON_Z1dUspD.png",
    "slug": "crimes-of-passion-1984",
    "stars": 4,
    "title": "Crimes of Passion",
    "year": "1984"
  }
]